DESCRIPTION.rst
LICENSE
MANIFEST.in
README.md
setup.py
libtools/__init__.py
libtools/_version.py
libtools/about.py
libtools/concurrency.py
libtools/environment.py
libtools/logd.py
libtools/numberfx.py
libtools/oscodes_unix.py
libtools/oscodes_win.py
libtools/progress.py
libtools/statics.py
libtools/time.py
libtools/timer.py
libtools/userinput.py
libtools/usermessage.py
libtools/variables.py
libtools/colors/__init__.py
libtools/colors/colormap.py
libtools/colors/colors.py
libtools/common/__init__.py
libtools/common/environment.py
libtools/common/facilities.py
libtools/io/__init__.py
libtools/io/binary.py
libtools/io/filesystem_ops.py
libtools/io/text.py
libtools/js/__init__.py
libtools/js/export.py
libtools/js/parse_json.py