Metadata-Version: 2.1
Name: libtools
Version: 0.4.2
Summary: Generic Tools & Utilities for processing i/o
Home-page: https://github.com/fstab50/libtools
Author: Blake Huber
Author-email: blakeca00@gmail.com
License: GPL-3.0
Keywords: code development tools
Classifier: Topic :: Software Development :: Build Tools
Classifier: Development Status :: 4 - Beta
Classifier: Programming Language :: Python :: 3.6
Classifier: Programming Language :: Python :: 3.7
Classifier: License :: OSI Approved :: GNU General Public License v3 (GPLv3)
Classifier: Operating System :: POSIX :: Linux
Requires-Python: >=3.6, <4
License-File: LICENSE
